{"conclusion":"success","createdAt":"2026-06-25T19:08:36Z","databaseId":28194099832,"displayTitle":"Merge pull request #194 from link-assistant/issue-193-2b86e2b9c679","event":"push","headBranch":"main","headSha":"b3d3eb82409fadbf3c11ee6dd0c4aa4b997c0ee5","jobs":[{"completedAt":"2026-06-25T19:08:48Z","conclusion":"success","databaseId":83516101284,"name":"Detect Changes","startedAt":"2026-06-25T19:08:39Z","status":"completed","steps":[{"completedAt":"2026-06-25T19:08:40Z","conclusion":"success","name":"Set up job","number":1,"startedAt":"2026-06-25T19:08:40Z","status":"completed"},{"completedAt":"2026-06-25T19:08:42Z","conclusion":"success","name":"Run actions/checkout@v6","number":2,"startedAt":"2026-06-25T19:08:40Z","status":"completed"},{"completedAt":"2026-06-25T19:08:46Z","conclusion":"success","name":"Setup Node.js","number":3,"startedAt":"2026-06-25T19:08:42Z","status":"completed"},{"completedAt":"2026-06-25T19:08:46Z","conclusion":"success","name":"Detect changes","number":4,"startedAt":"2026-06-25T19:08:46Z","status":"completed"},{"completedAt":"2026-06-25T19:08:46Z","conclusion":"success","name":"Post Setup Node.js","number":7,"startedAt":"2026-06-25T19:08:46Z","status":"completed"},{"completedAt":"2026-06-25T19:08:47Z","conclusion":"success","name":"Post Run actions/checkout@v6","number":8,"startedAt":"2026-06-25T19:08:46Z","status":"completed"},{"completedAt":"2026-06-25T19:08:47Z","conclusion":"success","name":"Complete job","number":9,"startedAt":"2026-06-25T19:08:47Z","status":"completed"}],"url":"https://github.com/link-assistant/calculator/actions/runs/28194099832/job/83516101284"},{"completedAt":"2026-06-25T19:08:37Z","conclusion":"skipped","databaseId":83516122031,"name":"Version Modification Check","startedAt":"2026-06-25T19:08:43Z","status":"completed","steps":[],"url":"https://github.com/link-assistant/calculator/actions/runs/28194099832/job/83516122031"},{"completedAt":"2026-06-25T19:08:37Z","conclusion":"skipped","databaseId":83516133225,"name":"Create Changelog PR","startedAt":"2026-06-25T19:08:47Z","status":"completed","steps":[],"url":"https://github.com/link-assistant/calculator/actions/runs/28194099832/job/83516133225"},{"completedAt":"2026-06-25T19:09:37Z","conclusion":"success","databaseId":83516137997,"name":"Lint and Format Check","startedAt":"2026-06-25T19:08:50Z","status":"completed","steps":[{"completedAt":"2026-06-25T19:08:52Z","conclusion":"success","name":"Set up job","number":1,"startedAt":"2026-06-25T19:08:51Z","status":"completed"},{"completedAt":"2026-06-25T19:08:53Z","conclusion":"success","name":"Run actions/checkout@v6","number":2,"startedAt":"2026-06-25T19:08:52Z","status":"completed"},{"completedAt":"2026-06-25T19:08:55Z","conclusion":"success","name":"Setup Rust","number":3,"startedAt":"2026-06-25T19:08:53Z","status":"completed"},{"completedAt":"2026-06-25T19:08:59Z","conclusion":"success","name":"Setup Node.js","number":4,"startedAt":"2026-06-25T19:08:55Z","status":"completed"},{"completedAt":"2026-06-25T19:09:02Z","conclusion":"success","name":"Cache cargo registry","number":5,"startedAt":"2026-06-25T19:08:59Z","status":"completed"},{"completedAt":"2026-06-25T19:09:05Z","conclusion":"success","name":"Check formatting","number":6,"startedAt":"2026-06-25T19:09:02Z","status":"completed"},{"completedAt":"2026-06-25T19:09:30Z","conclusion":"success","name":"Run Clippy","number":7,"startedAt":"2026-06-25T19:09:05Z","status":"completed"},{"completedAt":"2026-06-25T19:09:30Z","conclusion":"success","name":"Check file size limit","number":8,"startedAt":"2026-06-25T19:09:30Z","status":"completed"},{"completedAt":"2026-06-25T19:09:35Z","conclusion":"success","name":"Post Cache cargo registry","number":14,"startedAt":"2026-06-25T19:09:30Z","status":"completed"},{"completedAt":"2026-06-25T19:09:35Z","conclusion":"success","name":"Post Setup Node.js","number":15,"startedAt":"2026-06-25T19:09:35Z","status":"completed"},{"completedAt":"2026-06-25T19:09:35Z","conclusion":"success","name":"Post Run actions/checkout@v6","number":16,"startedAt":"2026-06-25T19:09:35Z","status":"completed"},{"completedAt":"2026-06-25T19:09:35Z","conclusion":"success","name":"Complete job","number":17,"startedAt":"2026-06-25T19:09:35Z","status":"completed"}],"url":"https://github.com/link-assistant/calculator/actions/runs/28194099832/job/83516137997"},{"completedAt":"2026-06-25T19:09:38Z","conclusion":"success","databaseId":83516138303,"name":"Test (ubuntu-latest)","startedAt":"2026-06-25T19:08:51Z","status":"completed","steps":[{"completedAt":"2026-06-25T19:08:52Z","conclusion":"success","name":"Set up job","number":1,"startedAt":"2026-06-25T19:08:52Z","status":"completed"},{"completedAt":"2026-06-25T19:08:54Z","conclusion":"success","name":"Run actions/checkout@v6","number":2,"startedAt":"2026-06-25T19:08:52Z","status":"completed"},{"completedAt":"2026-06-25T19:08:55Z","conclusion":"success","name":"Setup Rust","number":3,"startedAt":"2026-06-25T19:08:54Z","status":"completed"},{"completedAt":"2026-06-25T19:08:58Z","conclusion":"success","name":"Cache cargo registry","number":4,"startedAt":"2026-06-25T19:08:55Z","status":"completed"},{"completedAt":"2026-06-25T19:09:26Z","conclusion":"success","name":"Run tests","number":5,"startedAt":"2026-06-25T19:08:58Z","status":"completed"},{"completedAt":"2026-06-25T19:09:27Z","conclusion":"success","name":"Run doc tests","number":6,"startedAt":"2026-06-25T19:09:26Z","status":"completed"},{"completedAt":"2026-06-25T19:09:36Z","conclusion":"success","name":"Post Cache cargo registry","number":11,"startedAt":"2026-06-25T19:09:27Z","status":"completed"},{"completedAt":"2026-06-25T19:09:36Z","conclusion":"success","name":"Post Run actions/checkout@v6","number":12,"startedAt":"2026-06-25T19:09:36Z","status":"completed"},{"completedAt":"2026-06-25T19:09:36Z","conclusion":"success","name":"Complete job","number":13,"startedAt":"2026-06-25T19:09:36Z","status":"completed"}],"url":"https://github.com/link-assistant/calculator/actions/runs/28194099832/job/83516138303"},{"completedAt":"2026-06-25T19:08:48Z","conclusion":"skipped","databaseId":83516138971,"name":"Changelog Fragment Check","startedAt":"2026-06-25T19:08:49Z","status":"completed","steps":[],"url":"https://github.com/link-assistant/calculator/actions/runs/28194099832/job/83516138971"},{"completedAt":"2026-06-25T19:10:30Z","conclusion":"success","databaseId":83516298264,"name":"Build Package","startedAt":"2026-06-25T19:09:41Z","status":"completed","steps":[{"completedAt":"2026-06-25T19:09:42Z","conclusion":"success","name":"Set up job","number":1,"startedAt":"2026-06-25T19:09:41Z","status":"completed"},{"completedAt":"2026-06-25T19:09:44Z","conclusion":"success","name":"Run actions/checkout@v6","number":2,"startedAt":"2026-06-25T19:09:42Z","status":"completed"},{"completedAt":"2026-06-25T19:09:45Z","conclusion":"success","name":"Setup Rust","number":3,"startedAt":"2026-06-25T19:09:44Z","status":"completed"},{"completedAt":"2026-06-25T19:09:48Z","conclusion":"success","name":"Cache cargo registry","number":4,"startedAt":"2026-06-25T19:09:45Z","status":"completed"},{"completedAt":"2026-06-25T19:10:24Z","conclusion":"success","name":"Build release","number":5,"startedAt":"2026-06-25T19:09:48Z","status":"completed"},{"completedAt":"2026-06-25T19:10:24Z","conclusion":"success","name":"Check package","number":6,"startedAt":"2026-06-25T19:10:24Z","status":"completed"},{"completedAt":"2026-06-25T19:10:28Z","conclusion":"success","name":"Post Cache cargo registry","number":11,"startedAt":"2026-06-25T19:10:24Z","status":"completed"},{"completedAt":"2026-06-25T19:10:28Z","conclusion":"success","name":"Post Run actions/checkout@v6","number":12,"startedAt":"2026-06-25T19:10:28Z","status":"completed"},{"completedAt":"2026-06-25T19:10:28Z","conclusion":"success","name":"Complete job","number":13,"startedAt":"2026-06-25T19:10:28Z","status":"completed"}],"url":"https://github.com/link-assistant/calculator/actions/runs/28194099832/job/83516298264"},{"completedAt":"2026-06-25T19:10:40Z","conclusion":"success","databaseId":83516298268,"name":"WASM Build","startedAt":"2026-06-25T19:09:41Z","status":"completed","steps":[{"completedAt":"2026-06-25T19:09:43Z","conclusion":"success","name":"Set up job","number":1,"startedAt":"2026-06-25T19:09:42Z","status":"completed"},{"completedAt":"2026-06-25T19:09:46Z","conclusion":"success","name":"Run actions/checkout@v6","number":2,"startedAt":"2026-06-25T19:09:43Z","status":"completed"},{"completedAt":"2026-06-25T19:09:49Z","conclusion":"success","name":"Setup Rust","number":3,"startedAt":"2026-06-25T19:09:46Z","status":"completed"},{"completedAt":"2026-06-25T19:09:50Z","conclusion":"success","name":"Install wasm-pack","number":4,"startedAt":"2026-06-25T19:09:49Z","status":"completed"},{"completedAt":"2026-06-25T19:10:37Z","conclusion":"success","name":"Build WASM","number":5,"startedAt":"2026-06-25T19:09:50Z","status":"completed"},{"completedAt":"2026-06-25T19:10:38Z","conclusion":"success","name":"Post Run actions/checkout@v6","number":10,"startedAt":"2026-06-25T19:10:37Z","status":"completed"},{"completedAt":"2026-06-25T19:10:38Z","conclusion":"success","name":"Complete job","number":11,"startedAt":"2026-06-25T19:10:38Z","status":"completed"}],"url":"https://github.com/link-assistant/calculator/actions/runs/28194099832/job/83516298268"},{"completedAt":"2026-06-25T19:11:55Z","conclusion":"success","databaseId":83516462910,"name":"Auto Release","startedAt":"2026-06-25T19:10:32Z","status":"completed","steps":[{"completedAt":"2026-06-25T19:10:33Z","conclusion":"success","name":"Set up job","number":1,"startedAt":"2026-06-25T19:10:33Z","status":"completed"},{"completedAt":"2026-06-25T19:10:35Z","conclusion":"success","name":"Run actions/checkout@v6","number":2,"startedAt":"2026-06-25T19:10:33Z","status":"completed"},{"completedAt":"2026-06-25T19:10:36Z","conclusion":"success","name":"Setup Rust","number":3,"startedAt":"2026-06-25T19:10:35Z","status":"completed"},{"completedAt":"2026-06-25T19:10:40Z","conclusion":"success","name":"Setup Node.js","number":4,"startedAt":"2026-06-25T19:10:36Z","status":"completed"},{"completedAt":"2026-06-25T19:10:43Z","conclusion":"success","name":"Configure git","number":5,"startedAt":"2026-06-25T19:10:40Z","status":"completed"},{"completedAt":"2026-06-25T19:10:43Z","conclusion":"success","name":"Determine bump type from changelog fragments","number":6,"startedAt":"2026-06-25T19:10:43Z","status":"completed"},{"completedAt":"2026-06-25T19:10:44Z","conclusion":"success","name":"Check if version already released or no fragments","number":7,"startedAt":"2026-06-25T19:10:43Z","status":"completed"},{"completedAt":"2026-06-25T19:10:47Z","conclusion":"success","name":"Collect changelog and bump version","number":8,"startedAt":"2026-06-25T19:10:44Z","status":"completed"},{"completedAt":"2026-06-25T19:10:47Z","conclusion":"success","name":"Get current version","number":9,"startedAt":"2026-06-25T19:10:47Z","status":"completed"},{"completedAt":"2026-06-25T19:11:33Z","conclusion":"success","name":"Build release","number":10,"startedAt":"2026-06-25T19:10:47Z","status":"completed"},{"completedAt":"2026-06-25T19:11:53Z","conclusion":"success","name":"Publish to Crates.io","number":11,"startedAt":"2026-06-25T19:11:33Z","status":"completed"},{"completedAt":"2026-06-25T19:11:54Z","conclusion":"success","name":"Create GitHub Release","number":12,"startedAt":"2026-06-25T19:11:53Z","status":"completed"},{"completedAt":"2026-06-25T19:11:54Z","conclusion":"success","name":"Post Setup Node.js","number":23,"startedAt":"2026-06-25T19:11:54Z","status":"completed"},{"completedAt":"2026-06-25T19:11:54Z","conclusion":"success","name":"Post Run actions/checkout@v6","number":24,"startedAt":"2026-06-25T19:11:54Z","status":"completed"},{"completedAt":"2026-06-25T19:11:54Z","conclusion":"success","name":"Complete job","number":25,"startedAt":"2026-06-25T19:11:54Z","status":"completed"}],"url":"https://github.com/link-assistant/calculator/actions/runs/28194099832/job/83516462910"},{"completedAt":"2026-06-25T19:10:30Z","conclusion":"skipped","databaseId":83516463637,"name":"Instant Release","startedAt":"2026-06-25T19:10:30Z","status":"completed","steps":[],"url":"https://github.com/link-assistant/calculator/actions/runs/28194099832/job/83516463637"},{"completedAt":"2026-06-25T19:12:00Z","conclusion":"success","databaseId":83516495960,"name":"Web Build","startedAt":"2026-06-25T19:10:42Z","status":"completed","steps":[{"completedAt":"2026-06-25T19:10:43Z","conclusion":"success","name":"Set up job","number":1,"startedAt":"2026-06-25T19:10:43Z","status":"completed"},{"completedAt":"2026-06-25T19:10:45Z","conclusion":"success","name":"Run actions/checkout@v6","number":2,"startedAt":"2026-06-25T19:10:43Z","status":"completed"},{"completedAt":"2026-06-25T19:10:46Z","conclusion":"success","name":"Setup Rust","number":3,"startedAt":"2026-06-25T19:10:45Z","status":"completed"},{"completedAt":"2026-06-25T19:10:46Z","conclusion":"success","name":"Install wasm-pack","number":4,"startedAt":"2026-06-25T19:10:46Z","status":"completed"},{"completedAt":"2026-06-25T19:11:30Z","conclusion":"success","name":"Build WASM package","number":5,"startedAt":"2026-06-25T19:10:46Z","status":"completed"},{"completedAt":"2026-06-25T19:11:35Z","conclusion":"success","name":"Setup Node.js","number":6,"startedAt":"2026-06-25T19:11:30Z","status":"completed"},{"completedAt":"2026-06-25T19:11:39Z","conclusion":"success","name":"Install dependencies","number":7,"startedAt":"2026-06-25T19:11:35Z","status":"completed"},{"completedAt":"2026-06-25T19:11:39Z","conclusion":"success","name":"Copy currency data files to web public directory","number":8,"startedAt":"2026-06-25T19:11:39Z","status":"completed"},{"completedAt":"2026-06-25T19:11:42Z","conclusion":"success","name":"Type check","number":9,"startedAt":"2026-06-25T19:11:39Z","status":"completed"},{"completedAt":"2026-06-25T19:11:50Z","conclusion":"success","name":"Run web tests","number":10,"startedAt":"2026-06-25T19:11:42Z","status":"completed"},{"completedAt":"2026-06-25T19:11:58Z","conclusion":"success","name":"Build","number":11,"startedAt":"2026-06-25T19:11:50Z","status":"completed"},{"completedAt":"2026-06-25T19:11:58Z","conclusion":"success","name":"Upload web build artifact","number":12,"startedAt":"2026-06-25T19:11:58Z","status":"completed"},{"completedAt":"2026-06-25T19:11:59Z","conclusion":"success","name":"Post Setup Node.js","number":23,"startedAt":"2026-06-25T19:11:58Z","status":"completed"},{"completedAt":"2026-06-25T19:11:59Z","conclusion":"success","name":"Post Run actions/checkout@v6","number":24,"startedAt":"2026-06-25T19:11:59Z","status":"completed"},{"completedAt":"2026-06-25T19:11:59Z","conclusion":"success","name":"Complete job","number":25,"startedAt":"2026-06-25T19:11:59Z","status":"completed"}],"url":"https://github.com/link-assistant/calculator/actions/runs/28194099832/job/83516495960"},{"completedAt":"2026-06-25T19:12:53Z","conclusion":"success","databaseId":83516758136,"name":"Deploy to GitHub Pages","startedAt":"2026-06-25T19:12:05Z","status":"completed","steps":[{"completedAt":"2026-06-25T19:12:09Z","conclusion":"success","name":"Set up job","number":1,"startedAt":"2026-06-25T19:12:06Z","status":"completed"},{"completedAt":"2026-06-25T19:12:11Z","conclusion":"success","name":"Download web build artifact","number":2,"startedAt":"2026-06-25T19:12:10Z","status":"completed"},{"completedAt":"2026-06-25T19:12:12Z","conclusion":"success","name":"Setup Pages","number":3,"startedAt":"2026-06-25T19:12:11Z","status":"completed"},{"completedAt":"2026-06-25T19:12:14Z","conclusion":"success","name":"Upload artifact","number":4,"startedAt":"2026-06-25T19:12:12Z","status":"completed"},{"completedAt":"2026-06-25T19:12:52Z","conclusion":"success","name":"Deploy to GitHub Pages","number":5,"startedAt":"2026-06-25T19:12:14Z","status":"completed"},{"completedAt":"2026-06-25T19:12:52Z","conclusion":"success","name":"Complete job","number":6,"startedAt":"2026-06-25T19:12:52Z","status":"completed"}],"url":"https://github.com/link-assistant/calculator/actions/runs/28194099832/job/83516758136"},{"completedAt":"2026-06-25T19:14:05Z","conclusion":"success","databaseId":83516933013,"name":"Deploy Web After Release","startedAt":"2026-06-25T19:12:57Z","status":"completed","steps":[{"completedAt":"2026-06-25T19:12:59Z","conclusion":"success","name":"Set up job","number":1,"startedAt":"2026-06-25T19:12:58Z","status":"completed"},{"completedAt":"2026-06-25T19:13:01Z","conclusion":"success","name":"Run actions/checkout@v6","number":2,"startedAt":"2026-06-25T19:12:59Z","status":"completed"},{"completedAt":"2026-06-25T19:13:01Z","conclusion":"success","name":"Setup Rust","number":3,"startedAt":"2026-06-25T19:13:01Z","status":"completed"},{"completedAt":"2026-06-25T19:13:02Z","conclusion":"success","name":"Install wasm-pack","number":4,"startedAt":"2026-06-25T19:13:01Z","status":"completed"},{"completedAt":"2026-06-25T19:13:40Z","conclusion":"success","name":"Build WASM package with updated version","number":5,"startedAt":"2026-06-25T19:13:02Z","status":"completed"},{"completedAt":"2026-06-25T19:13:45Z","conclusion":"success","name":"Setup Node.js","number":6,"startedAt":"2026-06-25T19:13:40Z","status":"completed"},{"completedAt":"2026-06-25T19:13:49Z","conclusion":"success","name":"Install dependencies","number":7,"startedAt":"2026-06-25T19:13:45Z","status":"completed"},{"completedAt":"2026-06-25T19:13:49Z","conclusion":"success","name":"Copy currency data files to web public directory","number":8,"startedAt":"2026-06-25T19:13:49Z","status":"completed"},{"completedAt":"2026-06-25T19:13:56Z","conclusion":"success","name":"Build web app","number":9,"startedAt":"2026-06-25T19:13:49Z","status":"completed"},{"completedAt":"2026-06-25T19:13:56Z","conclusion":"success","name":"Setup Pages","number":10,"startedAt":"2026-06-25T19:13:56Z","status":"completed"},{"completedAt":"2026-06-25T19:13:57Z","conclusion":"success","name":"Upload artifact","number":11,"startedAt":"2026-06-25T19:13:56Z","status":"completed"},{"completedAt":"2026-06-25T19:14:03Z","conclusion":"success","name":"Deploy to GitHub Pages","number":12,"startedAt":"2026-06-25T19:13:57Z","status":"completed"},{"completedAt":"2026-06-25T19:14:03Z","conclusion":"success","name":"Post Setup Node.js","number":23,"startedAt":"2026-06-25T19:14:03Z","status":"completed"},{"completedAt":"2026-06-25T19:14:03Z","conclusion":"success","name":"Post Run actions/checkout@v6","number":24,"startedAt":"2026-06-25T19:14:03Z","status":"completed"},{"completedAt":"2026-06-25T19:14:03Z","conclusion":"success","name":"Complete job","number":25,"startedAt":"2026-06-25T19:14:03Z","status":"completed"}],"url":"https://github.com/link-assistant/calculator/actions/runs/28194099832/job/83516933013"},{"completedAt":"2026-06-25T19:16:17Z","conclusion":"success","databaseId":83517167037,"name":"Update Screenshots After Release / Update Screenshots","startedAt":"2026-06-25T19:14:08Z","status":"completed","steps":[{"completedAt":"2026-06-25T19:14:09Z","conclusion":"success","name":"Set up job","number":1,"startedAt":"2026-06-25T19:14:08Z","status":"completed"},{"completedAt":"2026-06-25T19:14:11Z","conclusion":"success","name":"Run actions/checkout@v6","number":2,"startedAt":"2026-06-25T19:14:09Z","status":"completed"},{"completedAt":"2026-06-25T19:14:12Z","conclusion":"success","name":"Setup Rust","number":3,"startedAt":"2026-06-25T19:14:11Z","status":"completed"},{"completedAt":"2026-06-25T19:14:12Z","conclusion":"success","name":"Install wasm-pack","number":4,"startedAt":"2026-06-25T19:14:12Z","status":"completed"},{"completedAt":"2026-06-25T19:14:51Z","conclusion":"success","name":"Build WASM package","number":5,"startedAt":"2026-06-25T19:14:12Z","status":"completed"},{"completedAt":"2026-06-25T19:14:57Z","conclusion":"success","name":"Setup Node.js","number":6,"startedAt":"2026-06-25T19:14:51Z","status":"completed"},{"completedAt":"2026-06-25T19:15:00Z","conclusion":"success","name":"Install web dependencies","number":7,"startedAt":"2026-06-25T19:14:57Z","status":"completed"},{"completedAt":"2026-06-25T19:15:19Z","conclusion":"success","name":"Install Playwright browsers","number":8,"startedAt":"2026-06-25T19:15:00Z","status":"completed"},{"completedAt":"2026-06-25T19:15:19Z","conclusion":"success","name":"Copy currency data files to web public directory","number":9,"startedAt":"2026-06-25T19:15:19Z","status":"completed"},{"completedAt":"2026-06-25T19:15:25Z","conclusion":"success","name":"Build web app","number":10,"startedAt":"2026-06-25T19:15:19Z","status":"completed"},{"completedAt":"2026-06-25T19:16:13Z","conclusion":"success","name":"Start preview server and take screenshots","number":11,"startedAt":"2026-06-25T19:15:25Z","status":"completed"},{"completedAt":"2026-06-25T19:16:13Z","conclusion":"skipped","name":"Upload screenshot failure artifacts","number":12,"startedAt":"2026-06-25T19:16:13Z","status":"completed"},{"completedAt":"2026-06-25T19:16:13Z","conclusion":"success","name":"Check for changes","number":13,"startedAt":"2026-06-25T19:16:13Z","status":"completed"},{"completedAt":"2026-06-25T19:16:15Z","conclusion":"success","name":"Commit and push changes","number":14,"startedAt":"2026-06-25T19:16:13Z","status":"completed"},{"completedAt":"2026-06-25T19:16:15Z","conclusion":"success","name":"Post Setup Node.js","number":27,"startedAt":"2026-06-25T19:16:15Z","status":"completed"},{"completedAt":"2026-06-25T19:16:15Z","conclusion":"success","name":"Post Run actions/checkout@v6","number":28,"startedAt":"2026-06-25T19:16:15Z","status":"completed"},{"completedAt":"2026-06-25T19:16:15Z","conclusion":"success","name":"Complete job","number":29,"startedAt":"2026-06-25T19:16:15Z","status":"completed"}],"url":"https://github.com/link-assistant/calculator/actions/runs/28194099832/job/83517167037"}],"name":"CI/CD Pipeline","status":"completed","updatedAt":"2026-06-25T19:16:18Z","url":"https://github.com/link-assistant/calculator/actions/runs/28194099832","workflowName":"CI/CD Pipeline"}
