{"assignees":[],"author":{"id":"MDQ6VXNlcjE0MzE5MDQ=","is_bot":false,"login":"konard","name":"Konstantin Diachenko"},"body":"formal-ai issue link-assistant/formal-ai#96 is integrating link-calculator as its delegated calculator backend and found one math-shaped expression that must stay on formal-ai's local fallback for now.\\n\\nReproduction with link-calculator v0.16.0:\\n\\n```text\\n100 - 25 % 7\\n```\\n\\nActual result:\\n\\n```text\\nResult: 99.75\\nLinks notation: (100 - (25 / 100))\\n```\\n\\nThe trailing `7` is not represented in the Links Notation or the steps. For calculator users, `%` can mean postfix percent in expressions like `8% of 0`, but it is also commonly used as binary remainder/modulo in programming/math-like prompts such as `100 - 25 % 7`.\\n\\nExpected behavior:\\n\\n- Either parse binary modulo/remainder for math-like infix usage, producing `96` for `100 - 25 % 7`; or\\n- reject the expression instead of accepting a prefix and dropping the trailing operand.\\n\\nA related prompt also shows why callers need strict full-input handling:\\n\\n```text\\n2 + 2 please\\n```\\n\\nActual result is `4 please`, because `please` is treated as a custom unit. Natural-language callers can strip wrappers before delegation, but the calculator should still avoid silently accepting unintended trailing text when possible.\\n\\nformal-ai workaround: keep English word-operator arithmetic and binary `%` remainder expressions on its local fallback until this behavior is supported upstream.","closedAt":null,"comments":[{"id":"IC_kwDORA5rcM8AAAABCnEzLw","author":{"login":"konard"},"authorAssociation":"MEMBER","body":"We need to download all logs and data related about the issue to this repository, make sure we compile that data to `./docs/case-studies/issue-{id}` folder, and use it to do deep case study analysis (also make sure to search online for additional facts and data), in which we will reconstruct timeline/sequence of events, list of each and all requirements from the issue, find root causes of the each problem, and propose possible solutions and solution plans for each requirement (we should also check known existing components/libraries, that solve similar problem or can help in solutions).\n\nIf there is not enough data to find actual root cause, add debug output and verbose mode if not present, that will allow us to find root cause on next iteration.\n\nIf issue related to any other repository/project, where we can report issues on GitHub, please do so. Each issue must contain reproducible examples, workarounds and suggestions for fix the issue in code.\n\nPlease plan and execute everything in this single pull request, you have unlimited time and context, as context auto-compacts and you can continue indefinitely, until it is each and every requirement fully addressed, and everything is totally done.","createdAt":"2026-05-17T09:33:16Z","includesCreatedEdit":false,"isMinimized":false,"minimizedReason":"","reactionGroups":[],"url":"https://github.com/link-assistant/calculator/issues/158#issuecomment-4470158127","viewerDidAuthor":true}],"createdAt":"2026-05-16T23:33:25Z","labels":[{"id":"LA_kwDORA5rcM8AAAACV689FA","name":"bug","description":"Something isn't working","color":"d73a4a"}],"number":158,"state":"OPEN","title":"Support binary modulo and reject trailing tokens after postfix percent","updatedAt":"2026-05-17T09:33:19Z","url":"https://github.com/link-assistant/calculator/issues/158"}
