{"author":{"id":"MDQ6VXNlcjE0MzE5MDQ=","is_bot":false,"login":"konard","name":"Konstantin Diachenko"},"baseRefName":"main","body":"## 🤖 AI-Powered Solution Draft\n\nThis pull request is being automatically generated to solve issue #156.\n\n### 📋 Issue Reference\nFixes #156\n\n### 🚧 Status\n**Work in Progress** - The AI assistant is currently analyzing and implementing the solution draft.\n\n### 📝 Implementation Details\n_Details will be added as the solution draft is developed..._\n\n---\n*This PR was created automatically by the AI issue solver*","createdAt":"2026-05-16T10:36:07Z","headRefName":"issue-156-492574dbd3ca","labels":[],"number":157,"state":"OPEN","title":"[WIP] Double check all functions and methods of Calculator are exportable as Rust library in crates","url":"https://github.com/link-assistant/calculator/pull/157"}
